personal_logger/__init__.py
personal_logger/cli.py
personal_logger/config.py
personal_logger/utils.py
personal_logger-0.1.3.dist-info/entry_points.txt
personal_logger-0.1.3.dist-info/WHEEL
personal_logger-0.1.3.dist-info/METADATA
personal_logger-0.1.3.dist-info/RECORD
