Metadata-Version: 2.1
Name: personal-logger
Version: 0.1.3
Summary: 
Home-page: https://github.com/tddschn/personal-logger
License: MIT
Keywords: utility
Author: Teddy Xinyuan Chen
Author-email: 45612704+tddschn@users.noreply.github.com
Requires-Python: >=3.10,<4.0
Classifier: License :: OSI Approved :: MIT License
Classifier: Programming Language :: Python :: 3
Classifier: Programming Language :: Python :: 3.10
Classifier: Topic :: Utilities
Requires-Dist: alfred-workflow-tddschn (>=0.1.5,<0.2.0)
Project-URL: Bug Tracker, https://github.com/tddschn/personal-logger/issues
Project-URL: Repository, https://github.com/tddschn/personal-logger
